<?xml version="1.0" encoding="utf-8"?>
<language>
	<entry name="AstraMilitarum0" value="Махар"/>
	<entry name="AstraMilitarum1" value="Бастоніўс"/>
	<entry name="AstraMilitarum2" value="Калігі"/>
	<entry name="AstraMilitarum3" value="Кайдэ"/>
	<entry name="AstraMilitarum4" value="Камір"/>
	<entry name="AstraMilitarum5" value="Драўн"/>
	<entry name="AstraMilitarum6" value="МакМэн"/>
	<entry name="AstraMilitarum7" value="Стракэн"/>
	<entry name="AstraMilitarum8" value="Тарік"/>
	<entry name="AstraMilitarum9" value="Рухман"/>
	<entry name="AstraMilitarum10" value="Кілен"/>
	<entry name="AstraMilitarum11" value="Брэднор"/>
	<entry name="AstraMilitarum12" value="Гратон"/>
	<entry name="AstraMilitarum13" value="Моніц"/>
	<entry name="AstraMilitarum14" value="Джото"/>
	<entry name="AstraMilitarum15" value="Чыкорскі"/>
	<entry name="AstraMilitarum16" value="Руц"/>
	<entry name="AstraMilitarum17" value="Грэванд"/>
	<entry name="AstraMilitarum18" value="Дадлі"/>
	<entry name="AstraMilitarum19" value="Скаўцоў"/>
	<entry name="AstraMilitarum20" value="Байксі"/>
	<entry name="AstraMilitarumCount" value="21"/>
	<entry name="ChaosSpaceMarines0" value="Люцыус"/>
	<entry name="ChaosSpaceMarines1" value="Хорус"/>
	<entry name="ChaosSpaceMarines2" value="Валяр'ян"/>
	<entry name="ChaosSpaceMarines3" value="Агрыпа"/>
	<entry name="ChaosSpaceMarines4" value="Морбус"/>
	<entry name="ChaosSpaceMarines5" value="Кэнкер"/>
	<entry name="ChaosSpaceMarines6" value="Озісмас"/>
	<entry name="ChaosSpaceMarines7" value="Філакс"/>
	<entry name="ChaosSpaceMarines8" value="Пугна"/>
	<entry name="ChaosSpaceMarines9" value="Рудзіс"/>
	<entry name="ChaosSpaceMarines10" value="Салпінкс"/>
	<entry name="ChaosSpaceMarines11" value="Табліфус"/>
	<entry name="ChaosSpaceMarines12" value="Йоварыян"/>
	<entry name="ChaosSpaceMarines13" value="Копіс"/>
	<entry name="ChaosSpaceMarines14" value="Драконіс"/>
	<entry name="ChaosSpaceMarines15" value="Папілус"/>
	<entry name="ChaosSpaceMarines16" value="Румпэнс"/>
	<entry name="ChaosSpaceMarines17" value="Энгран"/>
	<entry name="ChaosSpaceMarines18" value="Лібідус"/>
	<entry name="ChaosSpaceMarines19" value="Арціфіціён"/>
	<entry name="ChaosSpaceMarinesCount" value="20"/>
	<entry name="Eldar0" value="Агэйн звязаны смерцю"/>
	<entry name="Eldar1" value="Хайнацір паляўнічы"/>
	<entry name="Eldar2" value="Ткач блытаніны Асурыд"/>
	<entry name="Eldar3" value="Іньян песня ведзьмы"/>
	<entry name="Eldar4" value="Ліат зорны танцор"/>
	<entry name="Eldar5" value="Лілэр зорны бягун"/>
	<entry name="Eldar6" value="Курнеат сонечны выбух"/>
	<entry name="Eldar7" value="Старажытны Эльданос"/>
	<entry name="Eldar8" value="Дрэшор дзённая дзіда"/>
	<entry name="Eldar9" value="Эленіўм адважны"/>
	<entry name="Eldar10" value="Этех чкульптар"/>
	<entry name="Eldar11" value="Кондры арабацька"/>
	<entry name="Eldar12" value="Фі Ра"/>
	<entry name="Eldar13" value="Каранзар"/>
	<entry name="Eldar14" value="Артраган"/> 
	<entry name="Eldar15" value="Джайдрас нябачны"/>
	<entry name="Eldar16" value="Маўджык прысуд"/>
	<entry name="Eldar17" value="Ілан Ра"/>
	<entry name="Eldar18" value="Аўлірэль зорны майстар"/>
	<entry name="Eldar19" value="Ульціэль прывідны ўдар"/>
	<entry name="EldarCount" value="20"/>
	<entry name="Necrons0" value="Хуфех"/>
	<entry name="Necrons1" value="Амэнсэс"/> 
	<entry name="Necrons2" value="Азогард"/>
	<entry name="Necrons3" value="Варзіс"/>
	<entry name="Necrons4" value="Мэндрэх"/>
	<entry name="Necrons5" value="Занэс"/>
	<entry name="Necrons6" value="Джэт"/>
	<entry name="Necrons7" value="Сэмерхэт"/>
	<entry name="Necrons8" value="Нунетджэрх"/>
	<entry name="Necrons9" value="Сектыр"/> 
	<entry name="Necrons10" value="Анрахет"/>
	<entry name="Necrons11" value="Ахойрун"/>
	<entry name="Necrons12" value="Саўбехар"/>
	<entry name="Necrons13" value="Сахтех"/>
	<entry name="Necrons14" value="Менх"/>
	<entry name="Necrons15" value="Тех"/>
	<entry name="Necrons16" value="Номарх"/>
	<entry name="Necrons17" value="Неферзін"/>
	<entry name="Necrons18" value="Кендарх"/>
	<entry name="Necrons19" value="Грыліаполус"/>
	<entry name="NecronsCount" value="20"/>
	<entry name="Orks0" value="Скар"/>
	<entry name="Orks1" value="Жылезарыпа"/>
	<entry name="Orks2" value="Дуум"/>
	<entry name="Orks3" value="Гаргаш"/>
	<entry name="Orks4" value="Базгак"/>
	<entry name="Orks5" value="Бэдтуф"/>
	<entry name="Orks6" value="Горснік"/>
	<entry name="Orks7" value="Вурдака"/>
	<entry name="Orks8" value="Вотсіт"/>
	<entry name="Orks9" value="Жылезагрог"/>
	<entry name="Orks10" value="Крашрыпер"/>
	<entry name="Orks11" value="Ургрубд"/>
	<entry name="Orks12" value="Моркрэк"/>
	<entry name="Orks13" value="Угскав"/>
	<entry name="Orks14" value="Углуг"/>
	<entry name="Orks15" value="Фрагкрак"/> 
	<entry name="Orks16" value="Туфбос"/>
	<entry name="Orks17" value="Вотшок"/>
	<entry name="Orks18" value="Цінгуц"/>
	<entry name="OrksCount" value="19"/>
	<entry name="SpaceMarines0" value="Суліўс"/>
	<entry name="SpaceMarines1" value="Даменіко"/>
	<entry name="SpaceMarines2" value="Хіпарчус"/>
	<entry name="SpaceMarines3" value="Фаэдрон"/>
	<entry name="SpaceMarines4" value="Драко"/>
	<entry name="SpaceMarines5" value="Леонатус"/>
	<entry name="SpaceMarines6" value="Тэламон"/>
	<entry name="SpaceMarines7" value="Бэлерафон"/>
	<entry name="SpaceMarines8" value="Ясон"/>
	<entry name="SpaceMarines9" value="Меліагер"/>
	<entry name="SpaceMarines10" value="Асторыўс"/>
	<entry name="SpaceMarines11" value="Хаган"/>
	<entry name="SpaceMarines12" value="Пэрсэтэр"/>
	<entry name="SpaceMarines13" value="Хагані"/>
	<entry name="SpaceMarines14" value="Тарвіц"/>
	<entry name="SpaceMarines15" value="Пэнатэс"/>
	<entry name="SpaceMarines16" value="Ахілес"/>
	<entry name="SpaceMarines17" value="Аякс"/>
	<entry name="SpaceMarines18" value="Дзіамэлэс"/>
	<entry name="SpaceMarines19" value="Мерыянэс"/>
	<entry name="SpaceMarines20" value="Тэўксер"/>
	<entry name="SpaceMarinesCount" value="21"/>
	<entry name="Tyranids0" value="Азазоз"/>
	<entry name="Tyranids1" value="Хексаноз"/>
	<entry name="Tyranids2" value="Сазоз"/>
	<entry name="Tyranids3" value="Дзізала"/>
	<entry name="Tyranids4" value="Ктоха"/>
	<entry name="Tyranids5" value="Хастур"/>
	<entry name="Tyranids6" value="Мномгуах"/>
	<entry name="Tyranids7" value="Орн"/>
	<entry name="Tyranids8" value="Персэ"/>
	<entry name="Tyranids9" value="Шазак"/>
	<entry name="Tyranids10" value="Вайбур"/>
	<entry name="Tyranids11" value="Т’ла"/>
	<entry name="Tyranids12" value="Зушакон"/>
	<entry name="Tyranids13" value="Даолоз"/>
	<entry name="Tyranids14" value="Алкоз"/>
	<entry name="Tyranids15" value="Пізія"/> 
	<entry name="Tyranids16" value="Грэндэл"/>
	<entry name="Tyranids17" value="Хімаэра"/>
	<entry name="TyranidsCount" value="18"/>
	<entry name="Tau0" value="Камандуючы далёкі ўдар"/>
	<entry name="Tau1" value="Адмірал кананада"/>
	<entry name="Tau2" value="Амбасадар павольная гутарка"/>
	<entry name="Tau3" value="Планавальнік дапамога страху"/>
	<entry name="Tau4" value="Прынц самотны агонь"/>
	<entry name="Tau5" value="Камандуючы срэбны язык"/>
	<entry name="Tau6" value="Камандуючы няўлоўны звер"/>
	<entry name="Tau7" value="Камандуючы апякальная мудрасць"/>
	<entry name="Tau8" value="Камандуючы пустотная пастка"/>
	<entry name="Tau9" value="Камандуючы шырокі крок"/>
	<entry name="Tau10" value="Адмірал двайная асцярожнасць"/>
	<entry name="Tau11" value="Амбасадар старая казка"/>
	<entry name="Tau12" value="Планавальнік шмат талентў"/>
	<entry name="Tau13" value="Камандуючы схаваны ўдар"/>
	<entry name="Tau14" value="Прэлат вялікае сэрца"/> 
	<entry name="Tau15" value="Шанаванае непадпарадкаванне"/>
	<entry name="Tau16" value="Святая гвардыя"/>
	<entry name="Tau17" value="Камандуючы бяспечная думка"/>
	<entry name="Tau18" value="Камандуючы ззяючае падзенне"/>
	<entry name="TauCount" value="19"/>
</language>